<?xml version="1.0" encoding="utf-8" ?><dwsync><file name="4Inst.css" server="Macintosh HD/Users/orangemr/Desktop/4InstServer/" local="3476017513" remote="-4611761864073817751" Dst="-1" /><file name="bootstrap.css" server="Macintosh HD/Users/orangemr/Desktop/4InstServer/" local="3476135197" remote="3322654306446974237" Dst="-1" /><file name="cssfun.css" server="Macintosh HD/Users/orangemr/Desktop/4InstServer/" local="3476048178" remote="-4611761864073787086" Dst="-1" /><file name="main.css" server="Macintosh HD/Users/orangemr/Desktop/4InstServer/" local="3476103807" remote="-4611761864073731457" Dst="-1" /><file name="photoUpload.css" server="Macintosh HD/Users/orangemr/Desktop/4InstServer/" local="3476113435" remote="3322654306446952475" Dst="-1" /><file name="profile.css" server="Macintosh HD/Users/orangemr/Desktop/4InstServer/" local="3475847956" remote="-4611761864073987308" Dst="-1" /><file name="4Inst.css" server="Macintosh HD/Users/Maximilian/Desktop/4InstServer/" local="3478030833" remote="319783739121895921" Dst="-1" /><file name="bootstrap.css" server="Macintosh HD/Users/Maximilian/Desktop/4InstServer/" local="3477082116" remote="319783739120947204" Dst="-1" /><file name="bootstrap.min.css" server="Macintosh HD/Users/Maximilian/Desktop/4InstServer/" local="3475157082" remote="319783739119022170" Dst="-1" /><file name="cssfun.css" server="Macintosh HD/Users/Maximilian/Desktop/4InstServer/" local="3476048178" remote="319783739119913266" Dst="-1" /><file name="main.css" server="Macintosh HD/Users/Maximilian/Desktop/4InstServer/" local="3476103807" remote="319783739119968895" Dst="-1" /><file name="photoUpload.css" server="Macintosh HD/Users/Maximilian/Desktop/4InstServer/" local="3476113435" remote="319783739119978523" Dst="-1" /><file name="profile.css" server="Macintosh HD/Users/Maximilian/Desktop/4InstServer/" local="3475847956" remote="319783739119713044" Dst="-1" /><file name="bootstrap-theme.css" server="Macintosh HD/Users/Maximilian/Desktop/4InstServer/" local="3475157082" remote="319783739119022170" Dst="-1" /><file name="bootstrap-theme.css.map" server="Macintosh HD/Users/Maximilian/Desktop/4InstServer/" local="3475157081" remote="319783739119022169" Dst="-1" /><file name="bootstrap-theme.min.css" server="Macintosh HD/Users/Maximilian/Desktop/4InstServer/" local="3475157082" remote="319783739119022170" Dst="-1" /><file name="bootstrap.css.map" server="Macintosh HD/Users/Maximilian/Desktop/4InstServer/" local="3475157081" remote="319783739119022169" Dst="-1" /><file name="style.css" server="Macintosh HD/Users/Maximilian/Desktop/4InstServer/" local="3478126199" remote="319783739121991287" Dst="-1" /><file name="profilestyle.css" server="Macintosh HD/Users/Maximilian/Desktop/4InstServer/" local="3478024659" remote="319783739121889747" Dst="-1" /></dwsync>